{"curve_independent": [{"code": "Rotated planar 7x7", "n_k_d": [49, 1, 7], "time_steps": 1, "error_model": "Correlated XZ", "decoder": "Rotated planar SMWPM (eta=0.5)", "error_probability": 0.05, "measurement_error_probability": 0.0, "n_run": 50, "n_success": 47, "n_fail": 3, "n_logical_commutations": [0, 3], "custom_totals": null, "error_weight_total": 106, "error_weight_pvar": 4.1056, "logical_failure_rate": 0.06, "physical_error_rate": 0.043265306122448985, "wall_time": 0.13063720054924488}, {"code": "Rotated planar 11x11", "n_k_d": [121, 1, 11], "time_steps": 1, "error_model": "Correlated XZ", "decoder": "Rotated planar SMWPM (eta=0.5)", "error_probability": 0.05, "measurement_error_probability": 0.0, "n_run": 50, "n_success": 48, "n_fail": 2, "n_logical_commutations": [2, 0], "custom_totals": null, "error_weight_total": 292, "error_weight_pvar": 7.8544, "logical_failure_rate": 0.04, "physical_error_rate": 0.048264462809917356, "wall_time": 0.32839422672986984}, {"code": "Rotated planar 15x15", "n_k_d": [225, 1, 15], "time_steps": 1, "error_model": "Correlated XZ", "decoder": "Rotated planar SMWPM (eta=0.5)", "error_probability": 0.05, "measurement_error_probability": 0.0, "n_run": 50, "n_success": 50, "n_fail": 0, "n_logical_commutations": [0, 0], "custom_totals": null, "error_weight_total": 521, "error_weight_pvar": 15.4836, "logical_failure_rate": 0.0, "physical_error_rate": 0.04631111111111111, "wall_time": 0.6707943119108677}, {"code": "Rotated planar 19x19", "n_k_d": [361, 1, 19], "time_steps": 1, "error_model": "Correlated XZ", "decoder": "Rotated planar SMWPM (eta=0.5)", "error_probability": 0.05, "measurement_error_probability": 0.0, "n_run": 50, "n_success": 50, "n_fail": 0, "n_logical_commutations": [0, 0], "custom_totals": null, "error_weight_total": 901, "error_weight_pvar": 42.0996, "logical_failure_rate": 0.0, "physical_error_rate": 0.049916897506925205, "wall_time": 1.442213436588645}, {"code": "Rotated planar 23x23", "n_k_d": [529, 1, 23], "time_steps": 1, "error_model": "Correlated XZ", "decoder": "Rotated planar SMWPM (eta=0.5)", "error_probability": 0.05, "measurement_error_probability": 0.0, "n_run": 50, "n_success": 50, "n_fail": 0, "n_logical_commutations": [0, 0], "custom_totals": null, "error_weight_total": 1181, "error_weight_pvar": 46.3556, "logical_failure_rate": 0.0, "physical_error_rate": 0.04465028355387524, "wall_time": 2.5148386638611555}, {"code": "Rotated planar 27x27", "n_k_d": [729, 1, 27], "time_steps": 1, "error_model": "Correlated XZ", "decoder": "Rotated planar SMWPM (eta=0.5)", "error_probability": 0.05, "measurement_error_probability": 0.0, "n_run": 50, "n_success": 50, "n_fail": 0, "n_logical_commutations": [0, 0], "custom_totals": null, "error_weight_total": 1613, "error_weight_pvar": 73.1524, "logical_failure_rate": 0.0, "physical_error_rate": 0.04425240054869684, "wall_time": 4.199786651879549}], "curve_independent_deg": [{"code": "Rotated planar 7x7", "n_k_d": [49, 1, 7], "time_steps": 1, "error_model": "Correlated XZ", "decoder": "Deg Rotated planar SMWPM (eta=0.5)", "error_probability": 0.05, "measurement_error_probability": 0.0, "n_run": 50, "n_success": 50, "n_fail": 0, "n_logical_commutations": [0, 0], "custom_totals": null, "error_weight_total": 98, "error_weight_pvar": 2.4783999999999997, "logical_failure_rate": 0.0, "physical_error_rate": 0.04, "wall_time": 0.17970349453389645}, {"code": "Rotated planar 11x11", "n_k_d": [121, 1, 11], "time_steps": 1, "error_model": "Correlated XZ", "decoder": "Deg Rotated planar SMWPM (eta=0.5)", "error_probability": 0.05, "measurement_error_probability": 0.0, "n_run": 50, "n_success": 50, "n_fail": 0, "n_logical_commutations": [0, 0], "custom_totals": null, "error_weight_total": 251, "error_weight_pvar": 7.5796, "logical_failure_rate": 0.0, "physical_error_rate": 0.041487603305785124, "wall_time": 0.43411130271852016}, {"code": "Rotated planar 15x15", "n_k_d": [225, 1, 15], "time_steps": 1, "error_model": "Correlated XZ", "decoder": "Deg Rotated planar SMWPM (eta=0.5)", "error_probability": 0.05, "measurement_error_probability": 0.0, "n_run": 50, "n_success": 49, "n_fail": 1, "n_logical_commutations": [1, 0], "custom_totals": null, "error_weight_total": 493, "error_weight_pvar": 22.720399999999998, "logical_failure_rate": 0.02, "physical_error_rate": 0.04382222222222223, "wall_time": 0.9728134553879499}, {"code": "Rotated planar 19x19", "n_k_d": [361, 1, 19], "time_steps": 1, "error_model": "Correlated XZ", "decoder": "Deg Rotated planar SMWPM (eta=0.5)", "error_probability": 0.05, "measurement_error_probability": 0.0, "n_run": 50, "n_success": 50, "n_fail": 0, "n_logical_commutations": [0, 0], "custom_totals": null, "error_weight_total": 742, "error_weight_pvar": 30.2544, "logical_failure_rate": 0.0, "physical_error_rate": 0.04110803324099723, "wall_time": 1.8109235670417547}, {"code": "Rotated planar 23x23", "n_k_d": [529, 1, 23], "time_steps": 1, "error_model": "Correlated XZ", "decoder": "Deg Rotated planar SMWPM (eta=0.5)", "error_probability": 0.05, "measurement_error_probability": 0.0, "n_run": 50, "n_success": 48, "n_fail": 2, "n_logical_commutations": [1, 1], "custom_totals": null, "error_weight_total": 1195, "error_weight_pvar": 46.49, "logical_failure_rate": 0.04, "physical_error_rate": 0.04517958412098299, "wall_time": 3.318097371608019}, {"code": "Rotated planar 27x27", "n_k_d": [729, 1, 27], "time_steps": 1, "error_model": "Correlated XZ", "decoder": "Deg Rotated planar SMWPM (eta=0.5)", "error_probability": 0.05, "measurement_error_probability": 0.0, "n_run": 50, "n_success": 50, "n_fail": 0, "n_logical_commutations": [0, 0], "custom_totals": null, "error_weight_total": 1761, "error_weight_pvar": 67.6516, "logical_failure_rate": 0.0, "physical_error_rate": 0.048312757201646093, "wall_time": 5.567433139309287}]}