{"curve_independent": [{"code": "Rotated planar 7x7", "n_k_d": [49, 1, 7], "time_steps": 1, "error_model": "Correlated XZ", "decoder": "Rotated planar SMWPM (eta=0.5)", "error_probability": 0.05, "measurement_error_probability": 0.0, "n_run": 50, "n_success": 49, "n_fail": 1, "n_logical_commutations": [0, 1], "custom_totals": null, "error_weight_total": 94, "error_weight_pvar": 3.7056, "logical_failure_rate": 0.02, "physical_error_rate": 0.038367346938775505, "wall_time": 0.12607205007225275}, {"code": "Rotated planar 11x11", "n_k_d": [121, 1, 11], "time_steps": 1, "error_model": "Correlated XZ", "decoder": "Rotated planar SMWPM (eta=0.5)", "error_probability": 0.05, "measurement_error_probability": 0.0, "n_run": 50, "n_success": 50, "n_fail": 0, "n_logical_commutations": [0, 0], "custom_totals": null, "error_weight_total": 293, "error_weight_pvar": 9.6804, "logical_failure_rate": 0.0, "physical_error_rate": 0.0484297520661157, "wall_time": 0.3232372933998704}, {"code": "Rotated planar 15x15", "n_k_d": [225, 1, 15], "time_steps": 1, "error_model": "Correlated XZ", "decoder": "Rotated planar SMWPM (eta=0.5)", "error_probability": 0.05, "measurement_error_probability": 0.0, "n_run": 50, "n_success": 49, "n_fail": 1, "n_logical_commutations": [0, 1], "custom_totals": null, "error_weight_total": 519, "error_weight_pvar": 19.5156, "logical_failure_rate": 0.02, "physical_error_rate": 0.04613333333333333, "wall_time": 0.6584251942113042}, {"code": "Rotated planar 19x19", "n_k_d": [361, 1, 19], "time_steps": 1, "error_model": "Correlated XZ", "decoder": "Rotated planar SMWPM (eta=0.5)", "error_probability": 0.05, "measurement_error_probability": 0.0, "n_run": 50, "n_success": 50, "n_fail": 0, "n_logical_commutations": [0, 0], "custom_totals": null, "error_weight_total": 762, "error_weight_pvar": 23.8224, "logical_failure_rate": 0.0, "physical_error_rate": 0.042216066481994455, "wall_time": 1.3984843976795673}, {"code": "Rotated planar 23x23", "n_k_d": [529, 1, 23], "time_steps": 1, "error_model": "Correlated XZ", "decoder": "Rotated planar SMWPM (eta=0.5)", "error_probability": 0.05, "measurement_error_probability": 0.0, "n_run": 50, "n_success": 50, "n_fail": 0, "n_logical_commutations": [0, 0], "custom_totals": null, "error_weight_total": 1309, "error_weight_pvar": 53.7076, "logical_failure_rate": 0.0, "physical_error_rate": 0.04948960302457467, "wall_time": 2.6116437669843435}, {"code": "Rotated planar 27x27", "n_k_d": [729, 1, 27], "time_steps": 1, "error_model": "Correlated XZ", "decoder": "Rotated planar SMWPM (eta=0.5)", "error_probability": 0.05, "measurement_error_probability": 0.0, "n_run": 50, "n_success": 50, "n_fail": 0, "n_logical_commutations": [0, 0], "custom_totals": null, "error_weight_total": 1737, "error_weight_pvar": 52.5124, "logical_failure_rate": 0.0, "physical_error_rate": 0.04765432098765432, "wall_time": 4.425004467368126}], "curve_independent_deg": [{"code": "Rotated planar 7x7", "n_k_d": [49, 1, 7], "time_steps": 1, "error_model": "Correlated XZ", "decoder": "Deg Rotated planar SMWPM (eta=0.5)", "error_probability": 0.05, "measurement_error_probability": 0.0, "n_run": 50, "n_success": 50, "n_fail": 0, "n_logical_commutations": [0, 0], "custom_totals": null, "error_weight_total": 94, "error_weight_pvar": 3.9055999999999997, "logical_failure_rate": 0.0, "physical_error_rate": 0.038367346938775505, "wall_time": 0.17497694678604603}, {"code": "Rotated planar 11x11", "n_k_d": [121, 1, 11], "time_steps": 1, "error_model": "Correlated XZ", "decoder": "Deg Rotated planar SMWPM (eta=0.5)", "error_probability": 0.05, "measurement_error_probability": 0.0, "n_run": 50, "n_success": 48, "n_fail": 2, "n_logical_commutations": [1, 2], "custom_totals": null, "error_weight_total": 287, "error_weight_pvar": 11.2324, "logical_failure_rate": 0.04, "physical_error_rate": 0.04743801652892562, "wall_time": 0.48574767354875803}, {"code": "Rotated planar 15x15", "n_k_d": [225, 1, 15], "time_steps": 1, "error_model": "Correlated XZ", "decoder": "Deg Rotated planar SMWPM (eta=0.5)", "error_probability": 0.05, "measurement_error_probability": 0.0, "n_run": 50, "n_success": 50, "n_fail": 0, "n_logical_commutations": [0, 0], "custom_totals": null, "error_weight_total": 500, "error_weight_pvar": 15.44, "logical_failure_rate": 0.0, "physical_error_rate": 0.044444444444444446, "wall_time": 0.9958950532600284}, {"code": "Rotated planar 19x19", "n_k_d": [361, 1, 19], "time_steps": 1, "error_model": "Correlated XZ", "decoder": "Deg Rotated planar SMWPM (eta=0.5)", "error_probability": 0.05, "measurement_error_probability": 0.0, "n_run": 50, "n_success": 48, "n_fail": 2, "n_logical_commutations": [1, 1], "custom_totals": null, "error_weight_total": 859, "error_weight_pvar": 39.1476, "logical_failure_rate": 0.04, "physical_error_rate": 0.047590027700831025, "wall_time": 2.063961927779019}, {"code": "Rotated planar 23x23", "n_k_d": [529, 1, 23], "time_steps": 1, "error_model": "Correlated XZ", "decoder": "Deg Rotated planar SMWPM (eta=0.5)", "error_probability": 0.05, "measurement_error_probability": 0.0, "n_run": 50, "n_success": 49, "n_fail": 1, "n_logical_commutations": [1, 0], "custom_totals": null, "error_weight_total": 1212, "error_weight_pvar": 55.1824, "logical_failure_rate": 0.02, "physical_error_rate": 0.045822306238185256, "wall_time": 3.5023899152874947}, {"code": "Rotated planar 27x27", "n_k_d": [729, 1, 27], "time_steps": 1, "error_model": "Correlated XZ", "decoder": "Deg Rotated planar SMWPM (eta=0.5)", "error_probability": 0.05, "measurement_error_probability": 0.0, "n_run": 50, "n_success": 50, "n_fail": 0, "n_logical_commutations": [0, 0], "custom_totals": null, "error_weight_total": 1659, "error_weight_pvar": 44.2676, "logical_failure_rate": 0.0, "physical_error_rate": 0.04551440329218107, "wall_time": 5.566076801158488}]}