{"curve_independent": [{"code": "Planar 3x3", "n_k_d": [13, 1, 3], "time_steps": 1, "error_model": "Correlated XZ", "decoder": "Planar MWPM Independent", "error_probability_1": 0.0, "error_probability": 0.027129195498412084, "measurement_error_probability": 0.0, "n_run": 5000, "n_success": 4883, "n_fail": 117, "n_logical_commutations": [68, 50], "custom_totals": null, "error_weight_total": 4967, "error_weight_pvar": 1.6525564400000001, "logical_failure_rate": 0.0234, "physical_error_rate": 0.07641538461538462, "wall_time": 2.4137010099366307}, {"code": "Planar 5x5", "n_k_d": [41, 1, 5], "time_steps": 1, "error_model": "Correlated XZ", "decoder": "Planar MWPM Independent", "error_probability_1": 0.0, "error_probability": 0.027129195498412084, "measurement_error_probability": 0.0, "n_run": 5000, "n_success": 4548, "n_fail": 452, "n_logical_commutations": [234, 229], "custom_totals": null, "error_weight_total": 19599, "error_weight_pvar": 6.2117679599999995, "logical_failure_rate": 0.0904, "physical_error_rate": 0.09560487804878048, "wall_time": 5.59737792937085}, {"code": "Planar 7x7", "n_k_d": [85, 1, 7], "time_steps": 1, "error_model": "Correlated XZ", "decoder": "Planar MWPM Independent", "error_probability_1": 0.0, "error_probability": 0.027129195498412084, "measurement_error_probability": 0.0, "n_run": 5000, "n_success": 4653, "n_fail": 347, "n_logical_commutations": [193, 160], "custom_totals": null, "error_weight_total": 41899, "error_weight_pvar": 14.34035196, "logical_failure_rate": 0.0694, "physical_error_rate": 0.09858588235294118, "wall_time": 12.000293665099889}, {"code": "Planar 9x9", "n_k_d": [145, 1, 9], "time_steps": 1, "error_model": "Correlated XZ", "decoder": "Planar MWPM Independent", "error_probability_1": 0.0, "error_probability": 0.027129195498412084, "measurement_error_probability": 0.0, "n_run": 5000, "n_success": 4729, "n_fail": 271, "n_logical_commutations": [135, 145], "custom_totals": null, "error_weight_total": 72990, "error_weight_pvar": 24.408796, "logical_failure_rate": 0.0542, "physical_error_rate": 0.1006758620689655, "wall_time": 25.692898822017014}, {"code": "Planar 11x11", "n_k_d": [221, 1, 11], "time_steps": 1, "error_model": "Correlated XZ", "decoder": "Planar MWPM Independent", "error_probability_1": 0.0, "error_probability": 0.027129195498412084, "measurement_error_probability": 0.0, "n_run": 5000, "n_success": 4766, "n_fail": 234, "n_logical_commutations": [120, 117], "custom_totals": null, "error_weight_total": 111103, "error_weight_pvar": 37.92793564, "logical_failure_rate": 0.0468, "physical_error_rate": 0.10054570135746607, "wall_time": 50.29950771201402}, {"code": "Planar 13x13", "n_k_d": [313, 1, 13], "time_steps": 1, "error_model": "Correlated XZ", "decoder": "Planar MWPM Independent", "error_probability_1": 0.0, "error_probability": 0.027129195498412084, "measurement_error_probability": 0.0, "n_run": 5000, "n_success": 4844, "n_fail": 156, "n_logical_commutations": [76, 82], "custom_totals": null, "error_weight_total": 159122, "error_weight_pvar": 54.19676464, "logical_failure_rate": 0.0312, "physical_error_rate": 0.10167539936102236, "wall_time": 96.51673646643758}, {"code": "Planar 15x15", "n_k_d": [421, 1, 15], "time_steps": 1, "error_model": "Correlated XZ", "decoder": "Planar MWPM Independent", "error_probability_1": 0.0, "error_probability": 0.027129195498412084, "measurement_error_probability": 0.0, "n_run": 5000, "n_success": 4859, "n_fail": 141, "n_logical_commutations": [66, 77], "custom_totals": null, "error_weight_total": 214640, "error_weight_pvar": 73.48561600000001, "logical_failure_rate": 0.0282, "physical_error_rate": 0.1019667458432304, "wall_time": 180.64896160690114}, {"code": "Planar 17x17", "n_k_d": [545, 1, 17], "time_steps": 1, "error_model": "Correlated XZ", "decoder": "Planar MWPM Independent", "error_probability_1": 0.0, "error_probability": 0.027129195498412084, "measurement_error_probability": 0.0, "n_run": 5000, "n_success": 4911, "n_fail": 89, "n_logical_commutations": [39, 51], "custom_totals": null, "error_weight_total": 276556, "error_weight_pvar": 94.68275456, "logical_failure_rate": 0.0178, "physical_error_rate": 0.10148844036697248, "wall_time": 312.6017233268358}, {"code": "Planar 19x19", "n_k_d": [685, 1, 19], "time_steps": 1, "error_model": "Correlated XZ", "decoder": "Planar MWPM Independent", "error_probability_1": 0.0, "error_probability": 0.027129195498412084, "measurement_error_probability": 0.0, "n_run": 5000, "n_success": 4922, "n_fail": 78, "n_logical_commutations": [35, 43], "custom_totals": null, "error_weight_total": 348866, "error_weight_pvar": 117.44656176, "logical_failure_rate": 0.0156, "physical_error_rate": 0.10185868613138686, "wall_time": 534.8196953306906}, {"code": "Planar 21x21", "n_k_d": [841, 1, 21], "time_steps": 1, "error_model": "Correlated XZ", "decoder": "Planar MWPM Independent", "error_probability_1": 0.0, "error_probability": 0.027129195498412084, "measurement_error_probability": 0.0, "n_run": 5000, "n_success": 4936, "n_fail": 64, "n_logical_commutations": [30, 35], "custom_totals": null, "error_weight_total": 427435, "error_weight_pvar": 144.433031, "logical_failure_rate": 0.0128, "physical_error_rate": 0.10164922711058264, "wall_time": 876.2727384772152}, {"code": "Planar 23x23", "n_k_d": [1013, 1, 23], "time_steps": 1, "error_model": "Correlated XZ", "decoder": "Planar MWPM Independent", "error_probability_1": 0.0, "error_probability": 0.027129195498412084, "measurement_error_probability": 0.0, "n_run": 5000, "n_success": 4953, "n_fail": 47, "n_logical_commutations": [26, 21], "custom_totals": null, "error_weight_total": 515945, "error_weight_pvar": 177.642879, "logical_failure_rate": 0.0094, "physical_error_rate": 0.10186475814412636, "wall_time": 1382.900165094994}, {"code": "Planar 25x25", "n_k_d": [1201, 1, 25], "time_steps": 1, "error_model": "Correlated XZ", "decoder": "Planar MWPM Independent", "error_probability_1": 0.0, "error_probability": 0.027129195498412084, "measurement_error_probability": 0.0, "n_run": 5000, "n_success": 4963, "n_fail": 37, "n_logical_commutations": [18, 19], "custom_totals": null, "error_weight_total": 611973, "error_weight_pvar": 213.12609084, "logical_failure_rate": 0.0074, "physical_error_rate": 0.10191057452123231, "wall_time": 2100.3278519259766}, {"code": "Planar 27x27", "n_k_d": [1405, 1, 27], "time_steps": 1, "error_model": "Correlated XZ", "decoder": "Planar MWPM Independent", "error_probability_1": 0.0, "error_probability": 0.027129195498412084, "measurement_error_probability": 0.0, "n_run": 5000, "n_success": 4972, "n_fail": 28, "n_logical_commutations": [15, 13], "custom_totals": null, "error_weight_total": 716926, "error_weight_pvar": 236.88282096, "logical_failure_rate": 0.0056, "physical_error_rate": 0.1020535231316726, "wall_time": 3200.108927213121}, {"code": "Planar 29x29", "n_k_d": [1625, 1, 29], "time_steps": 1, "error_model": "Correlated XZ", "decoder": "Planar MWPM Independent", "error_probability_1": 0.0, "error_probability": 0.027129195498412084, "measurement_error_probability": 0.0, "n_run": 5000, "n_success": 4975, "n_fail": 25, "n_logical_commutations": [9, 16], "custom_totals": null, "error_weight_total": 828734, "error_weight_pvar": 290.44988976, "logical_failure_rate": 0.005, "physical_error_rate": 0.10199803076923078, "wall_time": 4782.083445614204}], "curve_independent_deg": [{"code": "Planar 3x3", "n_k_d": [13, 1, 3], "time_steps": 1, "error_model": "Correlated XZ", "decoder": "Planar MWPM Independent Degenerate", "error_probability_1": 0.0, "error_probability": 0.027129195498412084, "measurement_error_probability": 0.0, "n_run": 5000, "n_success": 4843, "n_fail": 157, "n_logical_commutations": [73, 85], "custom_totals": null, "error_weight_total": 5058, "error_weight_pvar": 1.76146544, "logical_failure_rate": 0.0314, "physical_error_rate": 0.07781538461538462, "wall_time": 2.4448794438503683}, {"code": "Planar 5x5", "n_k_d": [41, 1, 5], "time_steps": 1, "error_model": "Correlated XZ", "decoder": "Planar MWPM Independent Degenerate", "error_probability_1": 0.0, "error_probability": 0.027129195498412084, "measurement_error_probability": 0.0, "n_run": 5000, "n_success": 4855, "n_fail": 145, "n_logical_commutations": [75, 70], "custom_totals": null, "error_weight_total": 19515, "error_weight_pvar": 6.540791, "logical_failure_rate": 0.029, "physical_error_rate": 0.09519512195121951, "wall_time": 5.39523691823706}, {"code": "Planar 7x7", "n_k_d": [85, 1, 7], "time_steps": 1, "error_model": "Correlated XZ", "decoder": "Planar MWPM Independent Degenerate", "error_probability_1": 0.0, "error_probability": 0.027129195498412084, "measurement_error_probability": 0.0, "n_run": 5000, "n_success": 4885, "n_fail": 115, "n_logical_commutations": [65, 50], "custom_totals": null, "error_weight_total": 41963, "error_weight_pvar": 14.15446524, "logical_failure_rate": 0.023, "physical_error_rate": 0.0987364705882353, "wall_time": 11.989320595748723}, {"code": "Planar 9x9", "n_k_d": [145, 1, 9], "time_steps": 1, "error_model": "Correlated XZ", "decoder": "Planar MWPM Independent Degenerate", "error_probability_1": 0.0, "error_probability": 0.027129195498412084, "measurement_error_probability": 0.0, "n_run": 5000, "n_success": 4921, "n_fail": 79, "n_logical_commutations": [47, 32], "custom_totals": null, "error_weight_total": 72292, "error_weight_pvar": 24.82706944, "logical_failure_rate": 0.0158, "physical_error_rate": 0.09971310344827586, "wall_time": 25.838120847009122}, {"code": "Planar 11x11", "n_k_d": [221, 1, 11], "time_steps": 1, "error_model": "Correlated XZ", "decoder": "Planar MWPM Independent Degenerate", "error_probability_1": 0.0, "error_probability": 0.027129195498412084, "measurement_error_probability": 0.0, "n_run": 5000, "n_success": 4935, "n_fail": 65, "n_logical_commutations": [38, 28], "custom_totals": null, "error_weight_total": 111434, "error_weight_pvar": 37.75814576, "logical_failure_rate": 0.013, "physical_error_rate": 0.10084524886877827, "wall_time": 51.023565203882754}, {"code": "Planar 13x13", "n_k_d": [313, 1, 13], "time_steps": 1, "error_model": "Correlated XZ", "decoder": "Planar MWPM Independent Degenerate", "error_probability_1": 0.0, "error_probability": 0.027129195498412084, "measurement_error_probability": 0.0, "n_run": 5000, "n_success": 4959, "n_fail": 41, "n_logical_commutations": [23, 18], "custom_totals": null, "error_weight_total": 158932, "error_weight_pvar": 54.29677504, "logical_failure_rate": 0.0082, "physical_error_rate": 0.10155399361022364, "wall_time": 100.05583802238107}, {"code": "Planar 15x15", "n_k_d": [421, 1, 15], "time_steps": 1, "error_model": "Correlated XZ", "decoder": "Planar MWPM Independent Degenerate", "error_probability_1": 0.0, "error_probability": 0.027129195498412084, "measurement_error_probability": 0.0, "n_run": 5000, "n_success": 4974, "n_fail": 26, "n_logical_commutations": [13, 13], "custom_totals": null, "error_weight_total": 214180, "error_weight_pvar": 71.170704, "logical_failure_rate": 0.0052, "physical_error_rate": 0.10174821852731591, "wall_time": 183.9987480691634}, {"code": "Planar 17x17", "n_k_d": [545, 1, 17], "time_steps": 1, "error_model": "Correlated XZ", "decoder": "Planar MWPM Independent Degenerate", "error_probability_1": 0.0, "error_probability": 0.027129195498412084, "measurement_error_probability": 0.0, "n_run": 5000, "n_success": 4983, "n_fail": 17, "n_logical_commutations": [10, 7], "custom_totals": null, "error_weight_total": 275559, "error_weight_pvar": 95.93490076, "logical_failure_rate": 0.0034, "physical_error_rate": 0.10112256880733946, "wall_time": 330.02556351199746}, {"code": "Planar 19x19", "n_k_d": [685, 1, 19], "time_steps": 1, "error_model": "Correlated XZ", "decoder": "Planar MWPM Independent Degenerate", "error_probability_1": 0.0, "error_probability": 0.027129195498412084, "measurement_error_probability": 0.0, "n_run": 5000, "n_success": 4987, "n_fail": 13, "n_logical_commutations": [9, 4], "custom_totals": null, "error_weight_total": 347175, "error_weight_pvar": 120.410975, "logical_failure_rate": 0.0026, "physical_error_rate": 0.10136496350364962, "wall_time": 552.7572867739946}, {"code": "Planar 21x21", "n_k_d": [841, 1, 21], "time_steps": 1, "error_model": "Correlated XZ", "decoder": "Planar MWPM Independent Degenerate", "error_probability_1": 0.0, "error_probability": 0.027129195498412084, "measurement_error_probability": 0.0, "n_run": 5000, "n_success": 4998, "n_fail": 2, "n_logical_commutations": [2, 0], "custom_totals": null, "error_weight_total": 427799, "error_weight_pvar": 150.55042396, "logical_failure_rate": 0.0004, "physical_error_rate": 0.10173579072532699, "wall_time": 911.3899207501672}, {"code": "Planar 23x23", "n_k_d": [1013, 1, 23], "time_steps": 1, "error_model": "Correlated XZ", "decoder": "Planar MWPM Independent Degenerate", "error_probability_1": 0.0, "error_probability": 0.027129195498412084, "measurement_error_probability": 0.0, "n_run": 5000, "n_success": 4995, "n_fail": 5, "n_logical_commutations": [4, 1], "custom_totals": null, "error_weight_total": 516759, "error_weight_pvar": 172.77443676, "logical_failure_rate": 0.001, "physical_error_rate": 0.10202546890424481, "wall_time": 1471.2685376820154}, {"code": "Planar 25x25", "n_k_d": [1201, 1, 25], "time_steps": 1, "error_model": "Correlated XZ", "decoder": "Planar MWPM Independent Degenerate", "error_probability_1": 0.0, "error_probability": 0.027129195498412084, "measurement_error_probability": 0.0, "n_run": 5000, "n_success": 4998, "n_fail": 2, "n_logical_commutations": [1, 1], "custom_totals": null, "error_weight_total": 610952, "error_weight_pvar": 203.52494784, "logical_failure_rate": 0.0004, "physical_error_rate": 0.1017405495420483, "wall_time": 2167.907934172079}, {"code": "Planar 27x27", "n_k_d": [1405, 1, 27], "time_steps": 1, "error_model": "Correlated XZ", "decoder": "Planar MWPM Independent Degenerate", "error_probability_1": 0.0, "error_probability": 0.027129195498412084, "measurement_error_probability": 0.0, "n_run": 5000, "n_success": 5000, "n_fail": 0, "n_logical_commutations": [0, 0], "custom_totals": null, "error_weight_total": 714477, "error_weight_pvar": 240.76245884, "logical_failure_rate": 0.0, "physical_error_rate": 0.10170491103202847, "wall_time": 3330.9923104159534}, {"code": "Planar 29x29", "n_k_d": [1625, 1, 29], "time_steps": 1, "error_model": "Correlated XZ", "decoder": "Planar MWPM Independent Degenerate", "error_probability_1": 0.0, "error_probability": 0.027129195498412084, "measurement_error_probability": 0.0, "n_run": 5000, "n_success": 4998, "n_fail": 2, "n_logical_commutations": [1, 1], "custom_totals": null, "error_weight_total": 826805, "error_weight_pvar": 274.198279, "logical_failure_rate": 0.0004, "physical_error_rate": 0.10176061538461538, "wall_time": 5093.032100206241}]}